LICENSE
MANIFEST.in
README.md
ds9norm.py
setup.py
ds9norm.egg-info/PKG-INFO
ds9norm.egg-info/SOURCES.txt
ds9norm.egg-info/dependency_links.txt
ds9norm.egg-info/top_level.txt