Metadata-Version: 1.1
Name: ds9norm
Version: 0.1
Summary: A Matplotlib normalize object that replicates DS9 image stretching
Home-page: https://github.com/glue-viz/ds9norm
Author: Chris Beaumont
Author-email: cbeaumont@cfa.harvard.edu
License: MIT
Platform: UNKNOWN
Classifier: Development Status :: 4 - Beta
Classifier: Intended Audience :: Science/Research
Classifier: Environment :: Console
Classifier: Intended Audience :: Developers
Classifier: License :: OSI Approved :: MIT License
Classifier: Natural Language :: English
Classifier: Programming Language :: Python :: 2.6
Classifier: Programming Language :: Python :: 2.7
Classifier: Programming Language :: Python :: 3.3
Classifier: Programming Language :: Python :: 3.4
Classifier: Operating System :: OS Independent
Classifier: Topic :: Scientific/Engineering :: Visualization
